Metadata-Version: 2.4
Name: undatum
Version: 1.1.1
Summary: A powerful command-line tool for data processing and analysis
Home-page: https://github.com/datacoon/undatum/
Download-URL: https://github.com/datacoon/undatum/
Author: Ivan Begtin
Author-email: Ivan Begtin <ivan@begtin.tech>
License-Expression: MIT
Keywords: json,jsonl,csv,bson,cli,dataset,data-processing
Classifier: Development Status :: 5 - Production/Stable
Classifier: Programming Language :: Python
Classifier: Programming Language :: Python :: 3 :: Only
Classifier: Programming Language :: Python :: 3.9
Classifier: Environment :: Console
Classifier: Intended Audience :: Developers
Classifier: Intended Audience :: System Administrators
Classifier: Topic :: Software Development
Classifier: Topic :: System :: Networking
Classifier: Topic :: Terminals
Classifier: Topic :: Text Processing
Classifier: Topic :: Utilities
Requires-Python: >=3.9
License-File: LICENSE
Requires-Dist: avro>=1.10.2
Requires-Dist: chardet>=5.2.0
Requires-Dist: click>=8.0.3
Requires-Dist: duckdb
Requires-Dist: elasticsearch
Requires-Dist: iterabledata
Requires-Dist: jsonlines>=4.0.0
Requires-Dist: lz4>=4.3.2
Requires-Dist: mistql>=0.4.11
Requires-Dist: openpyxl>=3.1.2
Requires-Dist: orjson>=3.9.8
Requires-Dist: pandas>=2.0.3
Requires-Dist: py7zr>=0.20.6
Requires-Dist: pydantic
Requires-Dist: pymongo>=4.5.0
Requires-Dist: pyorc>=0.8.0
Requires-Dist: python-docx>=0.8.11
Requires-Dist: pyyaml
Requires-Dist: pyzstd
Requires-Dist: qddate>=1.0.4
Requires-Dist: requests
Requires-Dist: rich>=13.6.0
Requires-Dist: tabulate>=0.8.7
Requires-Dist: tqdm
Requires-Dist: typer
Requires-Dist: validators>=0.22.0
Requires-Dist: xlrd>=2.0.1
Requires-Dist: xlwt
Requires-Dist: xmltodict>=0.13.0
Requires-Dist: xxhash
Dynamic: author
Dynamic: download-url
Dynamic: home-page
Dynamic: license-file
Dynamic: requires-python
